iblocklist2ipset-0.0.1.dist-info/top_level.txt
iblocklist2ipset-0.0.1.dist-info/RECORD
iblocklist2ipset-0.0.1.dist-info/zip-safe
iblocklist2ipset-0.0.1.dist-info/METADATA
iblocklist2ipset-0.0.1.dist-info/DESCRIPTION.rst
iblocklist2ipset-0.0.1.dist-info/metadata.json
iblocklist2ipset-0.0.1.dist-info/entry_points.txt
iblocklist2ipset-0.0.1.dist-info/WHEEL
iblocklist2ipset/__init__.py
iblocklist2ipset/utils.py
iblocklist2ipset/ipset.py
iblocklist2ipset/cmd.py
iblocklist2ipset/networks.py
