Metadata-Version: 2.0
Name: iblocklist2ipset
Version: 0.0.1
Summary: Converter between P2P lists from IBlocklist.com to IPSet
Home-page: https://github.com/9seconds/iblocklist2ipset/
Author: Sergey Arkhipov
Author-email: serge@aerialsounds.org
License: MIT
Platform: UNKNOWN
Classifier: Development Status :: 4 - Beta
Classifier: Environment :: Console
Classifier: Intended Audience :: End Users/Desktop
Classifier: Intended Audience :: System Administrators
Classifier: License :: OSI Approved :: MIT License
Classifier: Operating System :: OS Independent
Classifier: Programming Language :: Python :: 2.6
Classifier: Programming Language :: Python :: 2.7
Classifier: Programming Language :: Python :: 3.2
Classifier: Programming Language :: Python :: 3.3
Classifier: Programming Language :: Python :: 3.4
Classifier: Programming Language :: Python :: 3.4
Classifier: Topic :: Internet :: WWW/HTTP :: Site Management :: Link Checking
Classifier: Topic :: System :: Networking :: Firewalls
Classifier: Topic :: Utilities
Requires-Dist: netaddr (==0.7.12)
Requires-Dist: requests (==2.3.0)
Requires-Dist: docopt (==0.6.2)
Requires-Dist: six (==1.7.3)
